knockapi/__init__.py
knockapi/_base_client.py
knockapi/_client.py
knockapi/_compat.py
knockapi/_constants.py
knockapi/_exceptions.py
knockapi/_files.py
knockapi/_models.py
knockapi/_qs.py
knockapi/_resource.py
knockapi/_response.py
knockapi/_streaming.py
knockapi/_types.py
knockapi/_version.py
knockapi/pagination.py
knockapi/py.typed
knockapi/_utils/__init__.py
knockapi/_utils/_compat.py
knockapi/_utils/_datetime_parse.py
knockapi/_utils/_logs.py
knockapi/_utils/_proxy.py
knockapi/_utils/_reflection.py
knockapi/_utils/_resources_proxy.py
knockapi/_utils/_streams.py
knockapi/_utils/_sync.py
knockapi/_utils/_transform.py
knockapi/_utils/_typing.py
knockapi/_utils/_utils.py
knockapi/lib/.keep
knockapi/resources/__init__.py
knockapi/resources/audiences.py
knockapi/resources/bulk_operations.py
knockapi/resources/workflows.py
knockapi/resources/channels/__init__.py
knockapi/resources/channels/bulk.py
knockapi/resources/channels/channels.py
knockapi/resources/integrations/__init__.py
knockapi/resources/integrations/census.py
knockapi/resources/integrations/hightouch.py
knockapi/resources/integrations/integrations.py
knockapi/resources/messages/__init__.py
knockapi/resources/messages/batch.py
knockapi/resources/messages/messages.py
knockapi/resources/objects/__init__.py
knockapi/resources/objects/bulk.py
knockapi/resources/objects/objects.py
knockapi/resources/providers/__init__.py
knockapi/resources/providers/ms_teams.py
knockapi/resources/providers/providers.py
knockapi/resources/providers/slack.py
knockapi/resources/schedules/__init__.py
knockapi/resources/schedules/bulk.py
knockapi/resources/schedules/schedules.py
knockapi/resources/tenants/__init__.py
knockapi/resources/tenants/bulk.py
knockapi/resources/tenants/tenants.py
knockapi/resources/users/__init__.py
knockapi/resources/users/bulk.py
knockapi/resources/users/feeds.py
knockapi/resources/users/guides.py
knockapi/resources/users/users.py
knockapi/types/__init__.py
knockapi/types/activity.py
knockapi-1.18.1.dist-info/METADATA
knockapi-1.18.1.dist-info/WHEEL
knockapi-1.18.1.dist-info/licenses/LICENSE
knockapi-1.18.1.dist-info/RECORD
